bensilence/__init__.py
bensilence/bensilence.py
bensilence-0.1.4.dist-info/LICENSE
bensilence-0.1.4.dist-info/METADATA
bensilence-0.1.4.dist-info/WHEEL
bensilence-0.1.4.dist-info/top_level.txt
bensilence-0.1.4.dist-info/RECORD
