Metadata-Version: 2.1
Name: bensilence
Version: 0.1.4
Summary: A Python library for recording voice using voice actvity detection (VAD). Best for AI voice assistants.
Home-page: https://github.com/benimrans/bensilence
Author: Imran (benimrans)
Author-email: abdullaimran997@example.com
Classifier: Programming Language :: Python :: 3
Classifier: License :: OSI Approved :: MIT License
Classifier: Operating System :: OS Independent
Requires-Python: >=3.7
License-File: LICENSE
Requires-Dist: numpy
Requires-Dist: pyaudio
Requires-Dist: pvcobra
Requires-Dist: soundfile
